Metadata-Version: 1.0
Name: prob-distrib
Version: 0.1
Summary: Gaussian and Binomial distributions
Home-page: UNKNOWN
Author: Grevians Onula
Author-email: grevians@yahoo.com
License: UNKNOWN
Platform: UNKNOWN
